pinku.py
Pinku-0.1.1.dist-info/DESCRIPTION.rst
Pinku-0.1.1.dist-info/METADATA
Pinku-0.1.1.dist-info/RECORD
Pinku-0.1.1.dist-info/WHEEL
Pinku-0.1.1.dist-info/entry_points.txt
Pinku-0.1.1.dist-info/metadata.json
Pinku-0.1.1.dist-info/top_level.txt
