Metadata-Version: 2.0
Name: Pinku
Version: 0.1.1
Summary: Pinboard-to-Buku importation utility
Home-page: https://github.com/mosegontar/pinku
Author: Alexander M. Gontar
Author-email: mosegontar@gmail.com
License: MIT
Platform: UNKNOWN
Classifier: License :: OSI Approved :: MIT License
Classifier: Programming Language :: Python :: 3 :: Only
Requires-Dist: buku
Requires-Dist: pinboard
